lama_cleaner/__init__.py
lama_cleaner/benchmark.py
lama_cleaner/const.py
lama_cleaner/helper.py
lama_cleaner/installer.py
lama_cleaner/model_manager.py
lama_cleaner/parse_args.py
lama_cleaner/runtime.py
lama_cleaner/schema.py
lama_cleaner/server.py
lama_cleaner/web_config.py
lama_cleaner/app/build/.DS_Store
lama_cleaner/app/build/asset-manifest.json
lama_cleaner/app/build/favicon.ico
lama_cleaner/app/build/index.html
lama_cleaner/app/build/static/css/main.6ca672e8.css
lama_cleaner/app/build/static/css/main.88f20861.css
lama_cleaner/app/build/static/css/main.ce986cc8.css
lama_cleaner/app/build/static/js/main.06abf3fb.js
lama_cleaner/app/build/static/js/main.06abf3fb.js.LICENSE.txt
lama_cleaner/app/build/static/js/main.1fda6320.js
lama_cleaner/app/build/static/js/main.1fda6320.js.LICENSE.txt
lama_cleaner/app/build/static/js/main.44aac645.js
lama_cleaner/app/build/static/js/main.44aac645.js.LICENSE.txt
lama_cleaner/app/build/static/media/Inter-Black.15ca31c0a2a68f76d2d1.woff2
lama_cleaner/app/build/static/media/Inter-Black.c6938660eec019fefd68.woff
lama_cleaner/app/build/static/media/Inter-BlackItalic.ca1e738e4f349f27514d.woff
lama_cleaner/app/build/static/media/Inter-BlackItalic.cb2a7335650c690077fe.woff2
lama_cleaner/app/build/static/media/Inter-Bold.93c1301bd9f486c573b3.woff
lama_cleaner/app/build/static/media/Inter-Bold.ec64ea577b0349e055ad.woff2
lama_cleaner/app/build/static/media/Inter-BoldItalic.2d26c56a606662486796.woff2
lama_cleaner/app/build/static/media/Inter-BoldItalic.b376885042f6c961a541.woff
lama_cleaner/app/build/static/media/Inter-ExtraBold.cbe0ae49c52c920fd563.woff2
lama_cleaner/app/build/static/media/Inter-ExtraBold.d0fa3bb2b7c9063dc594.woff
lama_cleaner/app/build/static/media/Inter-ExtraBoldItalic.535a6cf662596b3bd6a6.woff2
lama_cleaner/app/build/static/media/Inter-ExtraBoldItalic.6ab17abedc4d3f140953.woff
lama_cleaner/app/build/static/media/Inter-ExtraLight.72505e6a122c6acd5471.woff2
lama_cleaner-1.2.5.dist-info/LICENSE
lama_cleaner-1.2.5.dist-info/METADATA
lama_cleaner-1.2.5.dist-info/WHEEL
lama_cleaner-1.2.5.dist-info/entry_points.txt
lama_cleaner-1.2.5.dist-info/top_level.txt
lama_cleaner-1.2.5.dist-info/RECORD
