Metadata-Version: 2.1
Name: lama-cleaner
Version: 1.2.5
Summary: Image inpainting tool powered by SOTA AI Model
Home-page: https://github.com/Sanster/lama-cleaner
Author: PanicByte
Author-email: cwq1913@gmail.com
Classifier: License :: OSI Approved :: Apache Software License
Classifier: Operating System :: OS Independent
Classifier: Programming Language :: Python :: 3
Classifier: Programming Language :: Python :: 3.7
Classifier: Programming Language :: Python :: 3.8
Classifier: Programming Language :: Python :: 3.9
Classifier: Programming Language :: Python :: 3.10
Classifier: Topic :: Scientific/Engineering :: Artificial Intelligence
Requires-Python: >=3.7
License-File: LICENSE
Requires-Dist: torch (>=1.9.0)
Requires-Dist: opencv-python
Requires-Dist: flask (==2.2.3)
Requires-Dist: flask-socketio
Requires-Dist: simple-websocket
Requires-Dist: flask-cors
Requires-Dist: flaskwebgui (==0.3.5)
Requires-Dist: pydantic
Requires-Dist: rich
Requires-Dist: loguru
Requires-Dist: yacs
Requires-Dist: diffusers (==0.16.1)
Requires-Dist: transformers (==4.27.4)
Requires-Dist: gradio
Requires-Dist: piexif (==1.1.3)
Requires-Dist: safetensors
Requires-Dist: omegaconf
Requires-Dist: controlnet-aux (==0.0.3)
Requires-Dist: werkzeug (==2.2.2)
